bigledger/__about__.py
bigledger/__init__.py
bigledger-0.2.6.dist-info/METADATA
bigledger-0.2.6.dist-info/WHEEL
bigledger-0.2.6.dist-info/licenses/LICENSE.txt
bigledger-0.2.6.dist-info/RECORD
